MANIFEST.in
README.txt
setup.cfg
setup.py
docs/HISTORY.txt
docs/INSTALL.txt
docs/LICENSE.GPL
docs/LICENSE.txt
ploomcake/__init__.py
ploomcake/__init__.pyc
ploomcake.xhtmlstrict_theme.egg-info/PKG-INFO
ploomcake.xhtmlstrict_theme.egg-info/SOURCES.txt
ploomcake.xhtmlstrict_theme.egg-info/dependency_links.txt
ploomcake.xhtmlstrict_theme.egg-info/entry_points.txt
ploomcake.xhtmlstrict_theme.egg-info/namespace_packages.txt
ploomcake.xhtmlstrict_theme.egg-info/not-zip-safe
ploomcake.xhtmlstrict_theme.egg-info/requires.txt
ploomcake.xhtmlstrict_theme.egg-info/top_level.txt
ploomcake/xhtmlstrict_theme/__init__.py
ploomcake/xhtmlstrict_theme/configure.zcml
ploomcake/xhtmlstrict_theme/profiles.zcml
ploomcake/xhtmlstrict_theme/setuphandlers.py
ploomcake/xhtmlstrict_theme/skins.zcml
ploomcake/xhtmlstrict_theme/tests.py
ploomcake/xhtmlstrict_theme/version.txt
ploomcake/xhtmlstrict_theme/browser/__init__.py
ploomcake/xhtmlstrict_theme/browser/accessibility_actions.pt
ploomcake/xhtmlstrict_theme/browser/accessibility_actions.py
ploomcake/xhtmlstrict_theme/browser/colophon.pt
ploomcake/xhtmlstrict_theme/browser/common.py
ploomcake/xhtmlstrict_theme/browser/configure.zcml
ploomcake/xhtmlstrict_theme/browser/folder_contents.pt
ploomcake/xhtmlstrict_theme/browser/interfaces.py
ploomcake/xhtmlstrict_theme/browser/searchbox.pt
ploomcake/xhtmlstrict_theme/browser/sharing.pt
ploomcake/xhtmlstrict_theme/browser/sharing.py
ploomcake/xhtmlstrict_theme/locales/README.txt
ploomcake/xhtmlstrict_theme/profiles/default/jsregistry.xml
ploomcake/xhtmlstrict_theme/profiles/default/metadata.xml
ploomcake/xhtmlstrict_theme/profiles/default/ploomcake.xhtmlstrict_theme_various.txt
ploomcake/xhtmlstrict_theme/profiles/default/portlets.xml
ploomcake/xhtmlstrict_theme/profiles/default/skins.xml
ploomcake/xhtmlstrict_theme/profiles/default/viewlets.xml
ploomcake/xhtmlstrict_theme/skins/ploomcake_xhtmlstrict_theme/edit_macros.pt
ploomcake/xhtmlstrict_theme/skins/ploomcake_xhtmlstrict_theme/image_view_fullscreen.pt
ploomcake/xhtmlstrict_theme/skins/ploomcake_xhtmlstrict_theme/main_template.pt