Metadata-Version: 1.0
Name: ploomcake.xhtmlstrict-theme
Version: 0.1
Summary: This theme adds a xhtml strict templates to ploomcake.theme
Home-page: https://github.com/ploomcake/ploomcake.xhtmlstrict_theme
Author: Maurizio Lupo
Author-email: maurizio.lupo@redomino.com
License: GPL
Platform: UNKNOWN
Classifier: Framework :: Plone
Classifier: Programming Language :: Python
